logninja_guardian-0.1.0.dist-info/licenses/LICENSE
ninja_protection/__init__.py
ninja_protection/optimizer.py
logninja_guardian-0.1.0.dist-info/METADATA
logninja_guardian-0.1.0.dist-info/WHEEL
logninja_guardian-0.1.0.dist-info/entry_points.txt
logninja_guardian-0.1.0.dist-info/top_level.txt
logninja_guardian-0.1.0.dist-info/RECORD
