Metadata-Version: 2.4
Name: logninja-guardian
Version: 0.1.0
Summary: Interactive CLI tool for system optimization and monitoring using psutil (LOGGIE infrastructure)
Home-page: https://github.com/loggie-eth/ninja-protection
Author: loggie.eth
Author-email: founder@loggie.ai
License: MIT
Classifier: Development Status :: 3 - Alpha
Classifier: Intended Audience :: System Administrators
Classifier: License :: OSI Approved :: MIT License
Classifier: Operating System :: POSIX :: Linux
Classifier: Programming Language :: Python :: 3
Classifier: Topic :: System :: Monitoring
Classifier: Topic :: Utilities
Requires-Python: >=3.7
License-File: LICENSE
Requires-Dist: psutil
Requires-Dist: redis
Requires-Dist: termcolor
Dynamic: author
Dynamic: author-email
Dynamic: classifier
Dynamic: description
Dynamic: description-content-type
Dynamic: home-page
Dynamic: license
Dynamic: license-file
Dynamic: requires-dist
Dynamic: requires-python
Dynamic: summary
